filesense/__init__.py
filesense/file_renamer.py
filesense-1.0.1.dist-info/METADATA
filesense-1.0.1.dist-info/WHEEL
filesense-1.0.1.dist-info/top_level.txt
filesense-1.0.1.dist-info/RECORD
