Metadata-Version: 2.1
Name: filesense
Version: 1.0.1
Summary: A package to rename files based on their content using Generative AI.
Home-page: https://github.com/mayurd8862/FileSense.AI-Semantic-File-Renamer
Author: Mayur Dabade
Author-email: mayurdabade1103@gmail.com
Classifier: Programming Language :: Python :: 3
Classifier: License :: OSI Approved :: MIT License
Requires-Python: >=3.6
Requires-Dist: langchain-community
Requires-Dist: pypdf
Requires-Dist: google-generativeai
Requires-Dist: pillow
Requires-Dist: docx2txt
Requires-Dist: unstructured
Requires-Dist: python-pptx
